<?xml version='1.0' encoding='ASCII'?>
<bsim:definitions xmlns:bsim="http://bsim.hpi.uni-potsdam.de/scylla/simModel" targetNamespace="http://www.hpi.de">
  <bsim:simulationConfiguration id="qbp_51ff4970-7dda-42dd-8731-152d28cf4779" processRef="proc_703504298" processInstances="225" startDateTime="2017-08-14T08:00:00.000Z" resourceAssignmentOrder="priority,simulationTime">
    <bsim:task id="node_b29b90ab-a522-4356-8148-2eea6713e260" name="SALIDAEGRESO">
      <bsim:duration timeUnit="SECONDS">
        <bsim:constantDistribution>
          <bsim:constantValue>0</bsim:constantValue>
        </bsim:constantDistribution>
      </bsim:duration>
      <bsim:resources>
        <bsim:resource id="Role_5" amount="1"/>
      </bsim:resources>
    </bsim:task>
    <bsim:task id="node_3909fbec-066f-4e1b-b2c3-d4cfef99650d" name="EGRESOADMISION">
      <bsim:duration timeUnit="SECONDS">
        <bsim:constantDistribution>
          <bsim:constantValue>0</bsim:constantValue>
        </bsim:constantDistribution>
      </bsim:duration>
      <bsim:resources>
        <bsim:resource id="Role_4" amount="1"/>
      </bsim:resources>
    </bsim:task>
    <bsim:task id="node_96c52362-b715-4d50-9949-fe6f3791c830" name="ATENCIONCONSULTA">
      <bsim:duration timeUnit="SECONDS">
        <bsim:constantDistribution>
          <bsim:constantValue>0</bsim:constantValue>
        </bsim:constantDistribution>
      </bsim:duration>
      <bsim:resources>
        <bsim:resource id="Role_7" amount="1"/>
      </bsim:resources>
    </bsim:task>
    <bsim:task id="node_b145ed25-d49a-45a9-93f7-14f8272f449c" name="INGRESOADMISION">
      <bsim:duration timeUnit="SECONDS">
        <bsim:constantDistribution>
          <bsim:constantValue>0</bsim:constantValue>
        </bsim:constantDistribution>
      </bsim:duration>
      <bsim:resources>
        <bsim:resource id="Role_3" amount="1"/>
      </bsim:resources>
    </bsim:task>
    <bsim:task id="node_90caa9a4-4454-4002-8525-eff3bbcef27e" name="Folio">
      <bsim:duration timeUnit="SECONDS">
        <bsim:exponentialDistribution>
          <bsim:mean>967.2</bsim:mean>
        </bsim:exponentialDistribution>
      </bsim:duration>
      <bsim:resources>
        <bsim:resource id="Role_6" amount="1"/>
      </bsim:resources>
    </bsim:task>
    <bsim:task id="node_e32cbf6e-1fe9-4b36-a78e-4614c2a35157" name="TRIAGE">
      <bsim:duration timeUnit="SECONDS">
        <bsim:normalDistribution>
          <bsim:mean>462.3</bsim:mean>
          <bsim:standardDeviation>282.3</bsim:standardDeviation>
        </bsim:normalDistribution>
      </bsim:duration>
      <bsim:resources>
        <bsim:resource id="Role_2" amount="1"/>
      </bsim:resources>
    </bsim:task>
    <bsim:task id="node_ecdf1d95-1744-4bcf-a393-5ff2076dd078" name="SALIDAURGENCIAS">
      <bsim:duration timeUnit="SECONDS">
        <bsim:constantDistribution>
          <bsim:constantValue>0</bsim:constantValue>
        </bsim:constantDistribution>
      </bsim:duration>
      <bsim:resources>
        <bsim:resource id="Role_8" amount="1"/>
      </bsim:resources>
    </bsim:task>
    <bsim:task id="node_0617214b-1f66-4863-b19c-ec0e14f1a526" name="REGISTROINFURGENCIA">
      <bsim:duration timeUnit="SECONDS">
        <bsim:constantDistribution>
          <bsim:constantValue>0</bsim:constantValue>
        </bsim:constantDistribution>
      </bsim:duration>
      <bsim:resources>
        <bsim:resource id="Role_12" amount="1"/>
      </bsim:resources>
    </bsim:task>
    <bsim:task id="node_bab87d45-8c65-41b2-84ec-e30dba53d0e1" name="DIGITURNO">
      <bsim:duration timeUnit="SECONDS">
        <bsim:exponentialDistribution>
          <bsim:mean>343.4</bsim:mean>
        </bsim:exponentialDistribution>
      </bsim:duration>
      <bsim:resources>
        <bsim:resource id="Role_1" amount="1"/>
      </bsim:resources>
    </bsim:task>
    <bsim:task id="node_4cc948b5-4cc7-4071-96ed-f7120ed65868" name="HOSPITALIZACIONADMISION">
      <bsim:duration timeUnit="SECONDS">
        <bsim:constantDistribution>
          <bsim:constantValue>0</bsim:constantValue>
        </bsim:constantDistribution>
      </bsim:duration>
      <bsim:resources>
        <bsim:resource id="Role_10" amount="1"/>
      </bsim:resources>
    </bsim:task>
    <bsim:task id="node_50fcd1e5-edd0-4549-b3bd-4e601bb32960" name="FACTURACIONADMISION">
      <bsim:duration timeUnit="SECONDS">
        <bsim:constantDistribution>
          <bsim:constantValue>0</bsim:constantValue>
        </bsim:constantDistribution>
      </bsim:duration>
      <bsim:resources>
        <bsim:resource id="Role_9" amount="1"/>
      </bsim:resources>
    </bsim:task>
    <bsim:task id="node_6401a577-af9c-4e0e-9e04-60d4f9ac3de7" name="MUERTEEGRESO">
      <bsim:duration timeUnit="SECONDS">
        <bsim:constantDistribution>
          <bsim:constantValue>0</bsim:constantValue>
        </bsim:constantDistribution>
      </bsim:duration>
      <bsim:resources>
        <bsim:resource id="Role_11" amount="1"/>
      </bsim:resources>
    </bsim:task>
    <bsim:task id="node_f543b84b-51f8-4fef-ae4a-7cadb5032925" name="ANULACIONADMISION">
      <bsim:duration timeUnit="SECONDS">
        <bsim:constantDistribution>
          <bsim:constantValue>0</bsim:constantValue>
        </bsim:constantDistribution>
      </bsim:duration>
      <bsim:resources>
        <bsim:resource id="Role_13" amount="1"/>
      </bsim:resources>
    </bsim:task>
    <bsim:exclusiveGateway id="node_8726ffd5-f1fd-48cf-9a8d-773a8ca3e687">
      <bsim:outgoingSequenceFlow id="node_bf49af1e-3ad0-4725-a129-aedfa2b2b2b7">
        <bsim:branchingProbability>0.6</bsim:branchingProbability>
      </bsim:outgoingSequenceFlow>
      <bsim:outgoingSequenceFlow id="node_42c24a35-8053-4b3f-bb2e-8a6b95a032e4">
        <bsim:branchingProbability>0.4</bsim:branchingProbability>
      </bsim:outgoingSequenceFlow>
    </bsim:exclusiveGateway>
    <bsim:exclusiveGateway id="node_fd6a1758-4b0a-4b0a-9bda-6c90f7533023">
      <bsim:outgoingSequenceFlow id="node_a59807f4-8ab1-46ea-8ab9-883fdce4d355">
        <bsim:branchingProbability>0.0</bsim:branchingProbability>
      </bsim:outgoingSequenceFlow>
      <bsim:outgoingSequenceFlow id="node_f4e5b3ec-8969-4594-acda-47398214fade">
        <bsim:branchingProbability>1.0</bsim:branchingProbability>
      </bsim:outgoingSequenceFlow>
    </bsim:exclusiveGateway>
    <bsim:exclusiveGateway id="node_b80f4714-e006-4f87-9f01-806d844d058f">
      <bsim:outgoingSequenceFlow id="node_15c0e7bf-b5a8-45ac-addf-36934e1b6a5a">
        <bsim:branchingProbability>0.0</bsim:branchingProbability>
      </bsim:outgoingSequenceFlow>
      <bsim:outgoingSequenceFlow id="node_565e429b-9893-4fa4-85c0-5b952defacd8">
        <bsim:branchingProbability>1.0</bsim:branchingProbability>
      </bsim:outgoingSequenceFlow>
    </bsim:exclusiveGateway>
    <bsim:exclusiveGateway id="node_c9dfb0a5-fde9-4d0f-88f8-b3ecddb956dc">
      <bsim:outgoingSequenceFlow id="node_fb47c2b3-fa34-4492-b060-dddc9d9a78f5">
        <bsim:branchingProbability>0.51</bsim:branchingProbability>
      </bsim:outgoingSequenceFlow>
      <bsim:outgoingSequenceFlow id="node_a1f5e9d9-0d90-490c-951b-fea6215541e7">
        <bsim:branchingProbability>0.49</bsim:branchingProbability>
      </bsim:outgoingSequenceFlow>
    </bsim:exclusiveGateway>
    <bsim:exclusiveGateway id="node_ef1514c7-737d-47b0-9017-68e6f8c5c958">
      <bsim:outgoingSequenceFlow id="node_d0f3a127-971d-4cbe-a87a-2b7c253bee82">
        <bsim:branchingProbability>0.07</bsim:branchingProbability>
      </bsim:outgoingSequenceFlow>
      <bsim:outgoingSequenceFlow id="node_bccb5085-dffb-40e3-9bd3-df91a7e4b414">
        <bsim:branchingProbability>0.93</bsim:branchingProbability>
      </bsim:outgoingSequenceFlow>
    </bsim:exclusiveGateway>
    <bsim:startEvent id="node_06a2e032-fb32-4908-be21-8ee6e8a5fe02">
      <bsim:arrivalRate timeUnit="SECONDS">
        <bsim:uniformDistribution>
          <bsim:lower>4834.0</bsim:lower>
          <bsim:upper>33852.0</bsim:upper>
        </bsim:uniformDistribution>
      </bsim:arrivalRate>
    </bsim:startEvent>
  </bsim:simulationConfiguration>
</bsim:definitions>
